Metadata-Version: 2.1
Name: FalabellaAPIClient
Version: 0.0.1
Summary: Este paquete nos permite consumir el API de falabella
Home-page: https://github.com/andresroh/FalabellaAPIClient
Author: Camilo Andrés Rodríguez Higuera
Author-email: andres.roh@outlook.com
License: MIT
Keywords: python,alegra,alegra.com
Classifier: Development Status :: 3 - Alpha
Classifier: Intended Audience :: Developers
Classifier: Topic :: Software Development :: Build Tools
Classifier: License :: OSI Approved :: MIT License
Classifier: Programming Language :: Python :: 3
